mylib66/__init__.py
mylib66/general.py
mylib66/list.py
mylib66/math.py
mylib66/matplotlib.py
mylib66/numpy.py
mylib66-0.1.1.dist-info/LICENSE
mylib66-0.1.1.dist-info/METADATA
mylib66-0.1.1.dist-info/WHEEL
mylib66-0.1.1.dist-info/RECORD
